question_builder/__init__.py
question_builder/config.py
question_builder/initializer.py
question_builder/bp/__init__.py
question_builder/bp/dictionary_factory.py
question_builder/bp/question_builder.py
question_builder/bp/question_pack.py
question_builder/bp/question_creators/__init__.py
question_builder/bp/question_creators/antonym_question_creator.py
question_builder/bp/question_creators/choice_english_definitions_question_creator.py
question_builder/bp/question_creators/choice_spanish_definitions_question_creator.py
question_builder/bp/question_creators/conjugation_question_creator.py
question_builder/bp/question_creators/dual_video_question_creator.py
question_builder/bp/question_creators/dual_video_spanish_definitions_question_creator.py
question_builder/bp/question_creators/fullword_scrabble_question_creator.py
question_builder/bp/question_creators/fullword_typing_question_creator.py
question_builder/bp/question_creators/gap_question_creator.py
question_builder/bp/question_creators/intruder_question_creator.py
question_builder/bp/question_creators/means_like_question_creator.py
question_builder/bp/question_creators/minimal_pairs_question_creator.py
question_builder/bp/question_creators/multisynonym_question_creator.py
question_builder/bp/question_creators/partword_typing_question_creator.py
question_builder/bp/question_creators/pos_validators.py
question_builder/bp/question_creators/question_creator.py
question_builder/bp/question_creators/question_creator_exception.py
question_builder/bp/question_creators/relnoun_question_creator.py
question_builder/bp/question_creators/sentence_scrabble_question_creator.py
question_builder/bp/question_creators/simple_tense_choice_question_creator.py
question_builder/bp/question_creators/subword_question_creator.py
question_builder/bp/question_creators/synonym_question_creator.py
question_builder/bp/question_creators/tag_validators.py
question_builder/bp/question_creators/tense_verb_choice_question_creator.py
questiongeneratorcesar-0.0.9.dist-info/LICENSE
questiongeneratorcesar-0.0.9.dist-info/METADATA
questiongeneratorcesar-0.0.9.dist-info/WHEEL
questiongeneratorcesar-0.0.9.dist-info/top_level.txt
questiongeneratorcesar-0.0.9.dist-info/RECORD
